mongonow/__init__.py
mongonow/client.py
mongonow/collection.py
mongonow/database.py
mongonow/filter_parser.py
mongonow/json_manager.py
mongonow/path.py
mongonow/query_parser.py
mongonow/query_tokenizer.py
mongonow/type_checker.py
mongonow-0.0.16.dist-info/LICENSE
mongonow-0.0.16.dist-info/METADATA
mongonow-0.0.16.dist-info/WHEEL
mongonow-0.0.16.dist-info/top_level.txt
mongonow-0.0.16.dist-info/RECORD
