Metadata-Version: 2.1
Name: mongonow
Version: 0.0.16
Summary: MongoNow is the equivalent of sqlite for MongoDB. It's a local in-memory mongo-like database.
Home-page: https://github.com/AlexandreMahdhaoui/MongoNow
Author: Alexandre Mahdhaoui
Author-email: alexandre.mahdhaoui@gmail.com
License: MIT
Download-URL: https://github.com/AlexandreMahdhaoui/MongoNow.git
Keywords: mongodb,nosql
Platform: UNKNOWN
Classifier: License :: OSI Approved :: MIT License
License-File: LICENSE
